kopisapi/__init__.py
kopisapi/constants.py
kopisapi/get_request.py
kopisapi/kopis_api_requester.py
kopisapi/parser.py
kopisapi-0.1.2.dist-info/METADATA
kopisapi-0.1.2.dist-info/WHEEL
kopisapi-0.1.2.dist-info/top_level.txt
kopisapi-0.1.2.dist-info/RECORD
