Metadata-Version: 2.1
Name: kopisapi
Version: 0.1.2
Summary: This program provides data related to Korean performances.
Home-page: https://github.com/jinwooyoon/kopisapi
Author: jinwooyoon
Author-email: say_stop@naver.com
License: MIT license
Platform: UNKNOWN
Requires-Python: >=3
Requires-Dist: requests (==2.28.1)
Requires-Dist: xmltodict (==0.13.0)
